pimm/__init__.py
pimm/core.py
pimm/shared_memory.py
pimm/utils.py
pimm/world.py
pimm/tests/__init__.py
pimm/tests/test_shared_memory.py
pimm/tests/test_utils.py
pimm/tests/test_world.py
pimm/tests/testing.py
positronic/__init__.py
positronic/data_collection.py
positronic/replay_record.py
positronic/robot_controller.py
positronic/run_inference.py
positronic/assets/docs/dc_gui.png
positronic/assets/docs/server_screenshot.png
positronic/assets/mujoco/LICENSE
positronic/assets/mujoco/README.md
positronic/assets/mujoco/franka_table.assets.pkl
positronic/assets/mujoco/franka_table.xml
positronic/assets/mujoco/hand.xml
positronic/assets/mujoco/mjx_panda.xml
positronic/assets/mujoco/mjx_scene.xml
positronic/assets/mujoco/mjx_single_cube.xml
positronic/assets/mujoco/panda.png
positronic/assets/mujoco/panda.xml
positronic/assets/mujoco/panda_nohand.xml
positronic/assets/mujoco/scene.xml
positronic/assets/mujoco/assets/finger_0.obj
positronic/assets/mujoco/assets/finger_1.obj
positronic/assets/mujoco/assets/hand.stl
positronic/assets/mujoco/assets/hand_0.obj
positronic/assets/mujoco/assets/hand_1.obj
positronic/assets/mujoco/assets/hand_2.obj
positronic/assets/mujoco/assets/hand_3.obj
positronic/assets/mujoco/assets/hand_4.obj
positronic/assets/mujoco/assets/link0.stl
positronic/assets/mujoco/assets/link0_0.obj
positronic/assets/mujoco/assets/link0_1.obj
positronic/assets/mujoco/assets/link0_10.obj
positronic/assets/mujoco/assets/link0_11.obj
positronic/assets/mujoco/assets/link0_2.obj
positronic/assets/mujoco/assets/link0_3.obj
positronic/assets/mujoco/assets/link0_4.obj
positronic/assets/mujoco/assets/link0_5.obj
positronic/assets/mujoco/assets/link0_7.obj
positronic/assets/mujoco/assets/link0_8.obj
positronic/assets/mujoco/assets/link0_9.obj
positronic/assets/mujoco/assets/link1.obj
positronic/assets/mujoco/assets/link1.stl
positronic/assets/mujoco/assets/link2.obj
positronic/assets/mujoco/assets/link2.stl
positronic/assets/mujoco/assets/link3.stl
positronic-0.1.1.dist-info/licenses/LICENSE
positronic-0.1.1.dist-info/licenses/NOTICE
positronic-0.1.1.dist-info/METADATA
positronic-0.1.1.dist-info/WHEEL
positronic-0.1.1.dist-info/entry_points.txt
positronic-0.1.1.dist-info/top_level.txt
positronic-0.1.1.dist-info/RECORD
