Metadata-Version: 2.4
Name: positronic
Version: 0.1.1
Summary: Positronic robotics project
License:                                  Apache License
Classifier: License :: OSI Approved :: Apache Software License
Classifier: Programming Language :: Python :: 3
Classifier: Programming Language :: Python :: 3 :: Only
Requires-Python: >=3.11
License-File: LICENSE
License-File: NOTICE
Requires-Dist: av
Requires-Dist: configuronic>=0.2
Requires-Dist: cvxopt
Requires-Dist: dearpygui
Requires-Dist: dm_control
Requires-Dist: fastapi
Requires-Dist: fire
Requires-Dist: imageio[ffmpeg]
Requires-Dist: mujoco
Requires-Dist: numpy
Requires-Dist: opencv-python-headless
Requires-Dist: pyarrow
Requires-Dist: pyturbojpeg
Requires-Dist: robosuite
Requires-Dist: numba>=0.57
Requires-Dist: ruckig
Requires-Dist: scipy
Requires-Dist: torch
Requires-Dist: uvicorn[standard]
Requires-Dist: lerobot>=0.3.3
Requires-Dist: rerun-sdk~=0.22
Provides-Extra: hardware
Requires-Dist: feetech-servo-sdk; extra == "hardware"
Requires-Dist: positronic-franka; sys_platform == "linux" and extra == "hardware"
Requires-Dist: kortex_api; sys_platform == "linux" and extra == "hardware"
Requires-Dist: linuxpy; extra == "hardware"
Requires-Dist: pinocchio; extra == "hardware"
Requires-Dist: placo; extra == "hardware"
Requires-Dist: pyaudio; sys_platform == "linux" and extra == "hardware"
Requires-Dist: pymodbus; extra == "hardware"
Requires-Dist: pyserial; extra == "hardware"
Requires-Dist: pyzed; sys_platform == "linux" and extra == "hardware"
Provides-Extra: dev
Requires-Dist: ruff; extra == "dev"
Requires-Dist: pre-commit; extra == "dev"
Requires-Dist: ipython; extra == "dev"
Requires-Dist: jupyter; extra == "dev"
Requires-Dist: opencv-python; extra == "dev"
Requires-Dist: coverage; extra == "dev"
Requires-Dist: pytest-cov; extra == "dev"
Requires-Dist: pytest-asyncio; extra == "dev"
Requires-Dist: pytest-timeout; extra == "dev"
Requires-Dist: pytest; extra == "dev"
Requires-Dist: rerun-sdk[notebook]; extra == "dev"
Dynamic: license-file
